async_plus/__init__.py
async_plus/retry.py
async_plus/tasks.py
async_plus/typing.py
async_plus/wait.py
async_plus-0.3.0.dist-info/LICENSE
async_plus-0.3.0.dist-info/METADATA
async_plus-0.3.0.dist-info/WHEEL
async_plus-0.3.0.dist-info/top_level.txt
async_plus-0.3.0.dist-info/RECORD
