Metadata-Version: 2.1
Name: async-plus
Version: 0.3.0
Summary: Async-related stuff you miss in standard library
Home-page: https://github.com/ods/async-plus
Author: Denis Otkidach
Author-email: denis.otkidach@gmail.com
License: MIT
Platform: UNKNOWN
Requires-Python: >3.7
Provides-Extra: test
Requires-Dist: pytest (>=6.2.0) ; extra == 'test'
Requires-Dist: pytest-asyncio (>=0.14.0) ; extra == 'test'
Requires-Dist: pytest-cov (>=2.11.1) ; extra == 'test'
